MANIFEST.in
README.rst
setup.py
src/dj/__init__.py
src/dj.chain.egg-info/PKG-INFO
src/dj.chain.egg-info/SOURCES.txt
src/dj.chain.egg-info/dependency_links.txt
src/dj.chain.egg-info/namespace_packages.txt
src/dj.chain.egg-info/not-zip-safe
src/dj.chain.egg-info/requires.txt
src/dj.chain.egg-info/top_level.txt
src/dj/_chaintestproject/__init__.py
src/dj/_chaintestproject/manage.py
src/dj/_chaintestproject/settings.py
src/dj/_chaintestproject/urls.py
src/dj/_chaintestproject/app/__init__.py
src/dj/_chaintestproject/app/models.py
src/dj/chain/__init__.py
src/dj/chain/tests.py