Metadata-Version: 1.1
Name: dj.chain
Version: 0.9.0
Summary: An object that enables chaining multiple iterables to serve them lazily as a queryset-compatible object.
Home-page: https://github.com/ambv/dj.chain/
Author: Łukasz Langa
Author-email: lukasz@langa.pl
License: MIT
Keywords: django dj extra contrib chain iterator iteration queryset lazy
Platform: any
Classifier: Development Status :: 5 - Production/Stable
Classifier: Framework :: Django
Classifier: License :: OSI Approved :: MIT License
Classifier: Natural Language :: English
Classifier: Programming Language :: Python :: 2.7
Classifier: Programming Language :: Python :: 2 :: Only
Classifier: Programming Language :: Python
Classifier: Topic :: Internet :: WWW/HTTP
Classifier: Topic :: Software Development :: Libraries :: Python Modules
